examples/__init__.py
examples/utils/__init__.py
examples/utils/data_utils.py
minpy/__init__.py
minpy/array.py
minpy/context.py
minpy/core.py
minpy/primitive.py
minpy/tape.py
minpy/array_variants/__init__.py
minpy/array_variants/mxnet/__init__.py
minpy/array_variants/mxnet/mxnet_core.py
minpy/array_variants/mxnet/mxnet_wrapper.py
minpy/array_variants/mxnet/random.py
minpy/array_variants/numpy/__init__.py
minpy/array_variants/numpy/numpy_core.py
minpy/array_variants/numpy/numpy_wrapper.py
minpy/array_variants/numpy/random.py
minpy/dispatch/__init__.py
minpy/dispatch/policy.py
minpy/dispatch/primitive_selector.py
minpy/dispatch/registry.py
minpy/dispatch/rule.py
minpy/nn/__init__.py
minpy/nn/init.py
minpy/nn/io.py
minpy/nn/layers.py
minpy/nn/model.py
minpy/nn/model_builder.py
minpy/nn/modules.py
minpy/nn/optim.py
minpy/nn/solver.py
minpy/numpy/__init__.py
minpy/numpy/mocking.py
minpy/numpy/random.py
minpy/utils/__init__.py
minpy/utils/blacklist_generator.py
minpy/utils/common.py
minpy/utils/gradient_checker.py
minpy/utils/log.py
minpy/utils/minprof.py
minpy-0.3.4.data/data/VERSION
minpy-0.3.4.dist-info/DESCRIPTION.rst
minpy-0.3.4.dist-info/METADATA
minpy-0.3.4.dist-info/RECORD
minpy-0.3.4.dist-info/WHEEL
minpy-0.3.4.dist-info/metadata.json
minpy-0.3.4.dist-info/top_level.txt
