Metadata-Version: 2.0
Name: minpy
Version: 0.3.4
Summary: Pure NumPy practice with third-party operator integration.
Home-page: https://github.com/dmlc/minpy
Author: DMLC
Author-email: minerva-support@googlegroups.com
License: UNKNOWN
Platform: UNKNOWN
Requires-Dist: PyYAML
Requires-Dist: h5py
Requires-Dist: numpy
Requires-Dist: pillow
Requires-Dist: scipy
Requires-Dist: semantic-version
Requires-Dist: six
Requires-Dist: tabulate
